{"remainingRequest":"D:\\Project\\NaEditor\\node_modules\\awesome-typescript-loader\\dist\\entry.js!D:\\Project\\NaEditor\\node_modules\\thread-loader\\dist\\cjs.js!D:\\Project\\NaEditor\\src\\component\\FixedConfig\\FixedConfig.tsx","dependencies":[{"path":"D:\\Project\\NaEditor\\src\\component\\FixedConfig\\FixedConfig.tsx","mtime":1535074092000},{"path":"D:\\Project\\NaEditor\\src\\component\\FixedConfig\\FixedConfig.tsx","mtime":1535074092000},{"path":"D:\\Project\\NaEditor\\node_modules\\antd\\lib\\index.d.ts","mtime":499162500000},{"path":"D:\\Project\\NaEditor\\node_modules\\antd\\lib\\version\\index.d.ts","mtime":499162500000},{"path":"D:\\Project\\NaEditor\\node_modules\\antd\\lib\\upload\\index.d.ts","mtime":499162500000},{"path":"D:\\Project\\NaEditor\\node_modules\\antd\\lib\\upload\\Dragger.d.ts","mtime":499162500000},{"path":"D:\\Project\\NaEditor\\node_modules\\antd\\lib\\upload\\interface.d.ts","mtime":499162500000},{"path":"D:\\Project\\NaEditor\\node_modules\\@types\\react\\index.d.ts","mtime":1532389452000},{"path":"D:\\Project\\NaEditor\\node_modules\\@types\\react\\global.d.ts","mtime":1532389452000},{"path":"D:\\Project\\NaEditor\\node_modules\\csstype\\index.d.ts","mtime":1532213362000},{"path":"D:\\Project\\NaEditor\\node_modules\\antd\\lib\\upload\\Upload.d.ts","mtime":499162500000},{"path":"D:\\Project\\NaEditor\\node_modules\\antd\\lib\\upload\\utils.d.ts","mtime":499162500000},{"path":"D:\\Project\\NaEditor\\node_modules\\antd\\lib\\mention\\index.d.ts","mtime":499162500000},{"path":"D:\\Project\\NaEditor\\node_modules\\antd\\lib\\tooltip\\index.d.ts","mtime":499162500000},{"path":"D:\\Project\\NaEditor\\node_modules\\antd\\lib\\tooltip\\placements.d.ts","mtime":499162500000},{"path":"D:\\Project\\NaEditor\\node_modules\\antd\\lib\\timeline\\index.d.ts","mtime":499162500000},{"path":"D:\\Project\\NaEditor\\node_modules\\antd\\lib\\timeline\\TimelineItem.d.ts","mtime":499162500000},{"path":"D:\\Project\\NaEditor\\node_modules\\antd\\lib\\timeline\\Timeline.d.ts","mtime":499162500000},{"path":"D:\\Project\\NaEditor\\node_modules\\antd\\lib\\time-picker\\index.d.ts","mtime":499162500000},{"path":"D:\\Project\\NaEditor\\node_modules\\moment\\moment.d.ts","mtime":1527836312000},{"path":"D:\\Project\\NaEditor\\node_modules\\antd\\lib\\tag\\index.d.ts","mtime":499162500000},{"path":"D:\\Project\\NaEditor\\node_modules\\antd\\lib\\tag\\CheckableTag.d.ts","mtime":499162500000},{"path":"D:\\Project\\NaEditor\\node_modules\\antd\\lib\\tabs\\index.d.ts","mtime":499162500000},{"path":"D:\\Project\\NaEditor\\node_modules\\antd\\lib\\tree-select\\index.d.ts","mtime":499162500000},{"path":"D:\\Project\\NaEditor\\node_modules\\antd\\lib\\select\\index.d.ts","mtime":499162500000},{"path":"D:\\Project\\NaEditor\\node_modules\\antd\\lib\\tree-select\\interface.d.ts","mtime":499162500000},{"path":"D:\\Project\\NaEditor\\node_modules\\antd\\lib\\tree\\index.d.ts","mtime":499162500000},{"path":"D:\\Project\\NaEditor\\node_modules\\antd\\lib\\tree\\DirectoryTree.d.ts","mtime":499162500000},{"path":"D:\\Project\\NaEditor\\node_modules\\antd\\lib\\tree\\Tree.d.ts","mtime":499162500000},{"path":"D:\\Project\\NaEditor\\node_modules\\antd\\lib\\transfer\\index.d.ts","mtime":499162500000},{"path":"D:\\Project\\NaEditor\\node_modules\\antd\\lib\\transfer\\search.d.ts","mtime":499162500000},{"path":"D:\\Project\\NaEditor\\node_modules\\antd\\lib\\transfer\\operation.d.ts","mtime":499162500000},{"path":"D:\\Project\\NaEditor\\node_modules\\antd\\lib\\transfer\\list.d.ts","mtime":499162500000},{"path":"D:\\Project\\NaEditor\\node_modules\\antd\\lib\\table\\index.d.ts","mtime":499162500000},{"path":"D:\\Project\\NaEditor\\node_modules\\antd\\lib\\table\\interface.d.ts","mtime":499162500000},{"path":"D:\\Project\\NaEditor\\node_modules\\antd\\lib\\pagination\\index.d.ts","mtime":499162500000},{"path":"D:\\Project\\NaEditor\\node_modules\\antd\\lib\\pagination\\Pagination.d.ts","mtime":499162500000},{"path":"D:\\Project\\NaEditor\\node_modules\\antd\\lib\\checkbox\\index.d.ts","mtime":499162500000},{"path":"D:\\Project\\NaEditor\\node_modules\\antd\\lib\\checkbox\\Group.d.ts","mtime":499162500000},{"path":"D:\\Project\\NaEditor\\node_modules\\antd\\lib\\checkbox\\Checkbox.d.ts","mtime":499162500000},{"path":"D:\\Project\\NaEditor\\node_modules\\antd\\lib\\radio\\index.d.ts","mtime":499162500000},{"path":"D:\\Project\\NaEditor\\node_modules\\antd\\lib\\radio\\interface.d.ts","mtime":499162500000},{"path":"D:\\Project\\NaEditor\\node_modules\\antd\\lib\\radio\\radioButton.d.ts","mtime":499162500000},{"path":"D:\\Project\\NaEditor\\node_modules\\antd\\lib\\radio\\group.d.ts","mtime":499162500000},{"path":"D:\\Project\\NaEditor\\node_modules\\antd\\lib\\radio\\radio.d.ts","mtime":499162500000},{"path":"D:\\Project\\NaEditor\\node_modules\\antd\\lib\\table\\createStore.d.ts","mtime":499162500000},{"path":"D:\\Project\\NaEditor\\node_modules\\antd\\lib\\spin\\index.d.ts","mtime":499162500000},{"path":"D:\\Project\\NaEditor\\node_modules\\antd\\lib\\table\\Table.d.ts","mtime":499162500000},{"path":"D:\\Project\\NaEditor\\node_modules\\antd\\lib\\table\\ColumnGroup.d.ts","mtime":499162500000},{"path":"D:\\Project\\NaEditor\\node_modules\\antd\\lib\\table\\Column.d.ts","mtime":499162500000},{"path":"D:\\Project\\NaEditor\\node_modules\\antd\\lib\\switch\\index.d.ts","mtime":499162500000},{"path":"D:\\Project\\NaEditor\\node_modules\\antd\\lib\\steps\\index.d.ts","mtime":499162500000},{"path":"D:\\Project\\NaEditor\\node_modules\\antd\\lib\\slider\\index.d.ts","mtime":499162500000},{"path":"D:\\Project\\NaEditor\\node_modules\\antd\\lib\\row\\index.d.ts","mtime":499162500000},{"path":"D:\\Project\\NaEditor\\node_modules\\antd\\lib\\grid\\index.d.ts","mtime":499162500000},{"path":"D:\\Project\\NaEditor\\node_modules\\antd\\lib\\grid\\col.d.ts","mtime":499162500000},{"path":"D:\\Project\\NaEditor\\node_modules\\antd\\lib\\grid\\row.d.ts","mtime":499162500000},{"path":"D:\\Project\\NaEditor\\node_modules\\antd\\lib\\rate\\index.d.ts","mtime":499162500000},{"path":"D:\\Project\\NaEditor\\node_modules\\antd\\lib\\progress\\index.d.ts","mtime":499162500000},{"path":"D:\\Project\\NaEditor\\node_modules\\antd\\lib\\progress\\progress.d.ts","mtime":499162500000},{"path":"D:\\Project\\NaEditor\\node_modules\\antd\\lib\\popover\\index.d.ts","mtime":499162500000},{"path":"D:\\Project\\NaEditor\\node_modules\\antd\\lib\\popconfirm\\index.d.ts","mtime":499162500000},{"path":"D:\\Project\\NaEditor\\node_modules\\antd\\lib\\button\\button.d.ts","mtime":499162500000},{"path":"D:\\Project\\NaEditor\\node_modules\\antd\\lib\\button\\button-group.d.ts","mtime":499162500000},{"path":"D:\\Project\\NaEditor\\node_modules\\antd\\lib\\notification\\index.d.ts","mtime":499162500000},{"path":"D:\\Project\\NaEditor\\node_modules\\antd\\lib\\modal\\index.d.ts","mtime":499162500000},{"path":"D:\\Project\\NaEditor\\node_modules\\antd\\lib\\modal\\ActionButton.d.ts","mtime":499162500000},{"path":"D:\\Project\\NaEditor\\node_modules\\antd\\lib\\modal\\Modal.d.ts","mtime":499162500000},{"path":"D:\\Project\\NaEditor\\node_modules\\antd\\lib\\menu\\index.d.ts","mtime":499162500000},{"path":"D:\\Project\\NaEditor\\node_modules\\antd\\lib\\layout\\Sider.d.ts","mtime":499162500000},{"path":"D:\\Project\\NaEditor\\node_modules\\antd\\lib\\menu\\MenuItem.d.ts","mtime":499162500000},{"path":"D:\\Project\\NaEditor\\node_modules\\antd\\lib\\menu\\SubMenu.d.ts","mtime":499162500000},{"path":"D:\\Project\\NaEditor\\node_modules\\antd\\lib\\message\\index.d.ts","mtime":499162500000},{"path":"D:\\Project\\NaEditor\\node_modules\\antd\\lib\\locale-provider\\index.d.ts","mtime":499162500000},{"path":"D:\\Project\\NaEditor\\node_modules\\antd\\lib\\modal\\locale.d.ts","mtime":499162500000},{"path":"D:\\Project\\NaEditor\\node_modules\\antd\\lib\\list\\index.d.ts","mtime":499162500000},{"path":"D:\\Project\\NaEditor\\node_modules\\antd\\lib\\list\\Item.d.ts","mtime":499162500000},{"path":"D:\\Project\\NaEditor\\node_modules\\antd\\lib\\layout\\index.d.ts","mtime":499162500000},{"path":"D:\\Project\\NaEditor\\node_modules\\antd\\lib\\layout\\layout.d.ts","mtime":499162500000},{"path":"D:\\Project\\NaEditor\\node_modules\\antd\\lib\\input-number\\index.d.ts","mtime":499162500000},{"path":"D:\\Project\\NaEditor\\node_modules\\antd\\lib\\_util\\type.d.ts","mtime":499162500000},{"path":"D:\\Project\\NaEditor\\node_modules\\antd\\lib\\input\\index.d.ts","mtime":499162500000},{"path":"D:\\Project\\NaEditor\\node_modules\\antd\\lib\\input\\TextArea.d.ts","mtime":499162500000},{"path":"D:\\Project\\NaEditor\\node_modules\\antd\\lib\\input\\Search.d.ts","mtime":499162500000},{"path":"D:\\Project\\NaEditor\\node_modules\\antd\\lib\\input\\Input.d.ts","mtime":499162500000},{"path":"D:\\Project\\NaEditor\\node_modules\\antd\\lib\\input\\Group.d.ts","mtime":499162500000},{"path":"D:\\Project\\NaEditor\\node_modules\\antd\\lib\\icon\\index.d.ts","mtime":499162500000},{"path":"D:\\Project\\NaEditor\\node_modules\\antd\\lib\\form\\index.d.ts","mtime":499162500000},{"path":"D:\\Project\\NaEditor\\node_modules\\antd\\lib\\form\\FormItem.d.ts","mtime":499162500000},{"path":"D:\\Project\\NaEditor\\node_modules\\antd\\lib\\form\\Form.d.ts","mtime":499162500000},{"path":"D:\\Project\\NaEditor\\node_modules\\antd\\lib\\drawer\\index.d.ts","mtime":499162500000},{"path":"D:\\Project\\NaEditor\\node_modules\\antd\\lib\\dropdown\\index.d.ts","mtime":499162500000},{"path":"D:\\Project\\NaEditor\\node_modules\\antd\\lib\\dropdown\\dropdown-button.d.ts","mtime":499162500000},{"path":"D:\\Project\\NaEditor\\node_modules\\antd\\lib\\dropdown\\dropdown.d.ts","mtime":499162500000},{"path":"D:\\Project\\NaEditor\\node_modules\\antd\\lib\\divider\\index.d.ts","mtime":499162500000},{"path":"D:\\Project\\NaEditor\\node_modules\\antd\\lib\\date-picker\\index.d.ts","mtime":499162500000},{"path":"D:\\Project\\NaEditor\\node_modules\\antd\\lib\\date-picker\\interface.d.ts","mtime":499162500000},{"path":"D:\\Project\\NaEditor\\node_modules\\antd\\lib\\col\\index.d.ts","mtime":499162500000},{"path":"D:\\Project\\NaEditor\\node_modules\\antd\\lib\\cascader\\index.d.ts","mtime":499162500000},{"path":"D:\\Project\\NaEditor\\node_modules\\antd\\lib\\carousel\\index.d.ts","mtime":499162500000},{"path":"D:\\Project\\NaEditor\\node_modules\\antd\\lib\\collapse\\index.d.ts","mtime":499162500000},{"path":"D:\\Project\\NaEditor\\node_modules\\antd\\lib\\collapse\\CollapsePanel.d.ts","mtime":499162500000},{"path":"D:\\Project\\NaEditor\\node_modules\\antd\\lib\\collapse\\Collapse.d.ts","mtime":499162500000},{"path":"D:\\Project\\NaEditor\\node_modules\\antd\\lib\\card\\index.d.ts","mtime":499162500000},{"path":"D:\\Project\\NaEditor\\node_modules\\antd\\lib\\card\\Meta.d.ts","mtime":499162500000},{"path":"D:\\Project\\NaEditor\\node_modules\\antd\\lib\\card\\Grid.d.ts","mtime":499162500000},{"path":"D:\\Project\\NaEditor\\node_modules\\antd\\lib\\calendar\\index.d.ts","mtime":499162500000},{"path":"D:\\Project\\NaEditor\\node_modules\\antd\\lib\\calendar\\Header.d.ts","mtime":499162500000},{"path":"D:\\Project\\NaEditor\\node_modules\\antd\\lib\\button\\index.d.ts","mtime":499162500000},{"path":"D:\\Project\\NaEditor\\node_modules\\antd\\lib\\breadcrumb\\index.d.ts","mtime":499162500000},{"path":"D:\\Project\\NaEditor\\node_modules\\antd\\lib\\breadcrumb\\BreadcrumbItem.d.ts","mtime":499162500000},{"path":"D:\\Project\\NaEditor\\node_modules\\antd\\lib\\breadcrumb\\Breadcrumb.d.ts","mtime":499162500000},{"path":"D:\\Project\\NaEditor\\node_modules\\antd\\lib\\badge\\index.d.ts","mtime":499162500000},{"path":"D:\\Project\\NaEditor\\node_modules\\antd\\lib\\badge\\ScrollNumber.d.ts","mtime":499162500000},{"path":"D:\\Project\\NaEditor\\node_modules\\antd\\lib\\back-top\\index.d.ts","mtime":499162500000},{"path":"D:\\Project\\NaEditor\\node_modules\\antd\\lib\\avatar\\index.d.ts","mtime":499162500000},{"path":"D:\\Project\\NaEditor\\node_modules\\antd\\lib\\alert\\index.d.ts","mtime":499162500000},{"path":"D:\\Project\\NaEditor\\node_modules\\antd\\lib\\auto-complete\\index.d.ts","mtime":499162500000},{"path":"D:\\Project\\NaEditor\\node_modules\\antd\\lib\\anchor\\index.d.ts","mtime":499162500000},{"path":"D:\\Project\\NaEditor\\node_modules\\antd\\lib\\anchor\\AnchorLink.d.ts","mtime":499162500000},{"path":"D:\\Project\\NaEditor\\node_modules\\antd\\lib\\anchor\\Anchor.d.ts","mtime":499162500000},{"path":"D:\\Project\\NaEditor\\node_modules\\antd\\lib\\affix\\index.d.ts","mtime":499162500000},{"path":"D:\\Project\\NaEditor\\src\\component\\Hotspot\\index.ts","mtime":1535074092000},{"path":"D:\\Project\\NaEditor\\src\\component\\Hotspot\\Hotspot.tsx","mtime":1535074092000},{"path":"D:\\Project\\NaEditor\\src\\component\\Hotspot\\HotspotModal.tsx","mtime":1535074092000},{"path":"D:\\Project\\NaEditor\\src\\component\\Hotspot\\Area.tsx","mtime":1533698584000},{"path":"D:\\Project\\NaEditor\\src\\component\\interface.tsx","mtime":1533698584000},{"path":"D:\\Project\\NaEditor\\src\\component\\CarouselConfig\\interface.ts","mtime":1533698584000},{"path":"D:\\Project\\NaEditor\\src\\component\\ImageHotspotConfig\\interface.tsx","mtime":1533698584000},{"path":"D:\\Project\\NaEditor\\src\\component\\Hotspot\\HotspotLink.tsx","mtime":1533698584000},{"path":"D:\\Project\\NaEditor\\src\\OuterComponent.d.ts","mtime":1535074092000},{"path":"D:\\Project\\NaEditor\\src\\component\\PicLib\\index.ts","mtime":1533698584000},{"path":"D:\\Project\\NaEditor\\src\\component\\PicLib\\PicLib.tsx","mtime":1535074092000},{"path":"D:\\Project\\NaEditor\\src\\component\\PicLib\\PicLibModal.tsx","mtime":1535074092000},{"path":"D:\\Project\\NaEditor\\node_modules\\axios\\index.d.ts","mtime":1519077740000},{"path":"D:\\Project\\NaEditor\\src\\common\\script\\INTERFACE.ts","mtime":1535204665672},{"path":"D:\\Project\\NaEditor\\node_modules\\@types\\react-redux\\index.d.ts","mtime":1532389452000},{"path":"D:\\Project\\NaEditor\\node_modules\\@types\\react-redux\\node_modules\\redux\\index.d.ts","mtime":499162500000},{"path":"D:\\Project\\NaEditor\\node_modules\\cache-loader\\dist\\cjs.js","mtime":0},{"path":"D:\\Project\\NaEditor\\node_modules\\awesome-typescript-loader\\dist\\entry.js","mtime":1529596564000},{"path":"D:\\Project\\NaEditor\\node_modules\\thread-loader\\dist\\cjs.js","mtime":499162500000}],"contextDependencies":[],"result":["import * as React from 'react';\r\nimport { Component } from 'react';\r\nimport { connect } from 'react-redux';\r\nimport PicLib from '../PicLib';\r\nimport Hotspot from '../Hotspot';\r\nimport { Input, Select } from 'antd';\r\nconst Option = Select.Option;\r\nconst mapStateToProps = (state) => {\r\n    return {\r\n        moduleConfig: state.moduleConfig,\r\n    };\r\n};\r\nvar EHorizontalDir;\r\n(function (EHorizontalDir) {\r\n    EHorizontalDir[\"Left\"] = \"left\";\r\n    EHorizontalDir[\"Right\"] = \"right\";\r\n})(EHorizontalDir || (EHorizontalDir = {}));\r\nvar EVerticalDir;\r\n(function (EVerticalDir) {\r\n    EVerticalDir[\"Top\"] = \"top\";\r\n    EVerticalDir[\"Bottom\"] = \"bottom\";\r\n})(EVerticalDir || (EVerticalDir = {}));\r\nvar Unit;\r\n(function (Unit) {\r\n    Unit[\"percent\"] = \"%\";\r\n    Unit[\"px\"] = \"px\";\r\n})(Unit || (Unit = {}));\r\nclass FixedConfig extends Component {\r\n    constructor(props) {\r\n        super(props);\r\n        this.getConfigData = () => {\r\n            return this.state;\r\n        };\r\n        this.imgChange = (imgUrl) => {\r\n            this.setState({\r\n                imgUrl,\r\n            });\r\n        };\r\n        this.hotspotsChange = (hotspots) => {\r\n            this.setState({\r\n                hotspots,\r\n            });\r\n        };\r\n        const { moduleData: { data: { imgUrl, hotspots, horizontal, width, vertical, horizontalDir, verticalDir, horizontalUnit, verticalUnit, widthUnit, } } } = props;\r\n        this.state = {\r\n            imgUrl,\r\n            hotspots,\r\n            horizontal,\r\n            width,\r\n            vertical,\r\n            horizontalDir,\r\n            verticalDir,\r\n            horizontalUnit,\r\n            verticalUnit,\r\n            widthUnit,\r\n        };\r\n    }\r\n    toModuleData(configData) {\r\n        const { moduleConfig } = this.props;\r\n        const result = Object.assign({}, moduleConfig.moduleData, {\r\n            data: configData,\r\n        });\r\n        return result;\r\n    }\r\n    render() {\r\n        let { imgUrl, hotspots, horizontal, vertical, width, horizontalDir, verticalDir, horizontalUnit, verticalUnit, widthUnit, } = this.state;\r\n        const horizontalBefore = (React.createElement(Select, { defaultValue: horizontalDir || EHorizontalDir.Left, onChange: (horizontalDir) => { this.setState({ horizontalDir }); }, style: { width: 90 } },\r\n            React.createElement(Option, { value: EHorizontalDir.Left }, \"\\u8DDD\\u5DE6\\u8FB9\"),\r\n            React.createElement(Option, { value: EHorizontalDir.Right }, \"\\u8DDD\\u53F3\\u8FB9\")));\r\n        const verticalBefore = (React.createElement(Select, { defaultValue: verticalDir || EVerticalDir.Bottom, onChange: (verticalDir) => { this.setState({ verticalDir }); }, style: { width: 90 } },\r\n            React.createElement(Option, { value: EVerticalDir.Top }, \"\\u8DDD\\u9876\\u90E8\"),\r\n            React.createElement(Option, { value: EVerticalDir.Bottom }, \"\\u8DDD\\u5E95\\u90E8\")));\r\n        const horizontalAfter = (React.createElement(Select, { defaultValue: horizontalUnit || Unit.percent, onChange: (horizontalUnit) => { this.setState({ horizontalUnit }); }, style: { width: 50 } },\r\n            React.createElement(Option, { value: Unit.percent }, \"%\"),\r\n            React.createElement(Option, { value: Unit.px }, \"px\")));\r\n        const verticalAfter = (React.createElement(Select, { defaultValue: verticalUnit || Unit.percent, onChange: (verticalUnit) => { this.setState({ verticalUnit }); }, style: { width: 50 } },\r\n            React.createElement(Option, { value: Unit.percent }, \"%\"),\r\n            React.createElement(Option, { value: Unit.px }, \"px\")));\r\n        const widthAfter = (React.createElement(Select, { defaultValue: widthUnit || Unit.percent, onChange: (widthUnit) => { this.setState({ widthUnit }); }, style: { width: 50 } },\r\n            React.createElement(Option, { value: Unit.percent }, \"%\"),\r\n            React.createElement(Option, { value: Unit.px }, \"px\")));\r\n        return (React.createElement(\"div\", null,\r\n            React.createElement(\"p\", { className: \"d-title\" }, \"\\u56FE\\u7247\\u9009\\u62E9\"),\r\n            React.createElement(PicLib, { defaultValue: imgUrl, value: imgUrl, onChange: (imgUrl) => { this.imgChange(imgUrl); } }),\r\n            React.createElement(\"p\", { className: \"d-title\" }, \"\\u70ED\\u533A\\u914D\\u7F6E\"),\r\n            React.createElement(Hotspot, { imgs: [{ url: imgUrl }], hotspots: hotspots, onChange: this.hotspotsChange }),\r\n            React.createElement(\"p\", { className: \"d-title\" }, \"\\u5B9A\\u4F4D\\u4F4D\\u7F6E\"),\r\n            React.createElement(\"div\", null,\r\n                React.createElement(Input, { value: horizontal, onChange: (e) => { this.setState({ horizontal: e.target.value }); }, addonBefore: horizontalBefore, placeholder: \"\\u8BF7\\u8F93\\u5165\\u6570\\u5B57\", addonAfter: horizontalAfter })),\r\n            React.createElement(\"div\", { style: { marginTop: '10px' } },\r\n                React.createElement(Input, { value: vertical, onChange: (e) => { this.setState({ vertical: e.target.value }); }, addonBefore: verticalBefore, placeholder: \"\\u8BF7\\u8F93\\u5165\\u6570\\u5B57\", addonAfter: verticalAfter })),\r\n            React.createElement(\"div\", { style: { marginTop: '10px' } },\r\n                React.createElement(Input, { value: width, onChange: (e) => { this.setState({ width: e.target.value }); }, addonBefore: \"\\u5BBD\\u5EA6\", placeholder: \"\\u8BF7\\u8F93\\u5165\\u6570\\u5B57\", addonAfter: widthAfter }))));\r\n    }\r\n}\r\nexport default connect(mapStateToProps, {}, undefined, { withRef: true })(FixedConfig);\r\n",{"version":3,"file":"D:/Project/NaEditor/src/component/FixedConfig/FixedConfig.tsx","sourceRoot":"D:/Project/NaEditor/","sources":["node_modules\\thread-loader\\dist\\cjs.js!D:\\Project\\NaEditor\\src\\component\\FixedConfig\\FixedConfig.tsx"],"names":[],"mappings":"AAAA,OAAO,KAAK,KAAK,MAAM,OAAO,CAAC;AAC/B,OAAO,EAAE,SAAS,EAAE,MAAM,OAAO,CAAC;AAClC,OAAO,EAAE,OAAO,EAAE,MAAM,aAAa,CAAC;AAGtC,OAAO,MAAM,MAAM,WAAW,CAAC;AAC/B,OAAO,OAAO,MAAM,YAAY,CAAC;AACjC,OAAO,EAAE,KAAK,EAAE,MAAM,EAAE,MAAM,MAAM,CAAC;AACrC,MAAM,MAAM,GAAG,MAAM,CAAC,MAAM,CAAC;AAE7B,MAAM,eAAe,GAAG,CAAC,KAAa,EAAE,EAAE;IACtC,OAAO;QACH,YAAY,EAAE,KAAK,CAAC,YAAY;KACnC,CAAC;AACN,CAAC,CAAC;AAEF,IAAK,cAGJ;AAHD,WAAK,cAAc;IACf,+BAAa,CAAA;IACb,iCAAe,CAAA;AACnB,CAAC,EAHI,cAAc,KAAd,cAAc,QAGlB;AAED,IAAK,YAGJ;AAHD,WAAK,YAAY;IACb,2BAAW,CAAA;IACX,iCAAiB,CAAA;AACrB,CAAC,EAHI,YAAY,KAAZ,YAAY,QAGhB;AAED,IAAK,IAGJ;AAHD,WAAK,IAAI;IACL,qBAAa,CAAA;IACb,iBAAS,CAAA;AACb,CAAC,EAHI,IAAI,KAAJ,IAAI,QAGR;AAoBD,iBAAkB,SAAQ,SAA6C;IAEnE,YAAY,KAAuB;QAC/B,KAAK,CAAC,KAAK,CAAC,CAAC;QAgCjB,kBAAa,GAAG,GAAG,EAAE;YACjB,OAAO,IAAI,CAAC,KAAK,CAAC;QACtB,CAAC,CAAA;QAWD,cAAS,GAAG,CAAC,MAAc,EAAE,EAAE;YAC3B,IAAI,CAAC,QAAQ,CAAC;gBACV,MAAM;aACT,CAAC,CAAC;QACP,CAAC,CAAA;QAED,mBAAc,GAAG,CAAC,QAAuB,EAAE,EAAE;YACzC,IAAI,CAAC,QAAQ,CAAC;gBACV,QAAQ;aACX,CAAC,CAAC;QACP,CAAC,CAAA;QAtDG,MAAM,EACF,UAAU,EAAE,EACR,IAAI,EAAE,EACF,MAAM,EACN,QAAQ,EACR,UAAU,EACV,KAAK,EACL,QAAQ,EACR,aAAa,EACb,WAAW,EACX,cAAc,EACd,YAAY,EACZ,SAAS,GACZ,EACJ,EACJ,GAAG,KAAK,CAAC;QACV,IAAI,CAAC,KAAK,GAAG;YACT,MAAM;YACN,QAAQ;YACR,UAAU;YACV,KAAK;YACL,QAAQ;YACR,aAAa;YACb,WAAW;YACX,cAAc;YACd,YAAY;YACZ,SAAS;SACZ,CAAA;IACL,CAAC;IAOD,YAAY,CAAC,UAAe;QACxB,MAAM,EAAE,YAAY,EAAE,GAAG,IAAI,CAAC,KAAK,CAAC;QACpC,MAAM,MAAM,GAAG,MAAM,CAAC,MAAM,CAAC,EAAE,EAAE,YAAY,CAAC,UAAU,EAAE;YACtD,IAAI,EAAE,UAAU;SACnB,CAAC,CAAC;QACH,OAAO,MAAM,CAAC;IAClB,CAAC;IAeD,MAAM;QACF,IAAI,EAAE,MAAM,EACR,QAAQ,EACR,UAAU,EACV,QAAQ,EACR,KAAK,EACL,aAAa,EACb,WAAW,EACX,cAAc,EACd,YAAY,EACZ,SAAS,GACZ,GAAG,IAAI,CAAC,KAAK,CAAC;QAEf,MAAM,gBAAgB,GAAG,CACrB,oBAAC,MAAM,IACH,YAAY,EAAE,aAAa,IAAI,cAAc,CAAC,IAAI,EAClD,QAAQ,EAAE,CAAC,aAAkB,EAAE,EAAE,GAAG,IAAI,CAAC,QAAQ,CAAC,EAAE,aAAa,EAAE,CAAC,CAAC,CAAC,CAAC,EACvE,KAAK,EAAE,EAAE,KAAK,EAAE,EAAE,EAAE;YACpB,oBAAC,MAAM,IAAC,KAAK,EAAE,cAAc,CAAC,IAAI,yBAAc;YAChD,oBAAC,MAAM,IAAC,KAAK,EAAE,cAAc,CAAC,KAAK,yBAAc,CAC5C,CACZ,CAAC;QAEF,MAAM,cAAc,GAAG,CACnB,oBAAC,MAAM,IACH,YAAY,EAAE,WAAW,IAAI,YAAY,CAAC,MAAM,EAChD,QAAQ,EAAE,CAAC,WAAgB,EAAE,EAAE,GAAG,IAAI,CAAC,QAAQ,CAAC,EAAE,WAAW,EAAE,CAAC,CAAC,CAAC,CAAC,EACnE,KAAK,EAAE,EAAE,KAAK,EAAE,EAAE,EAAE;YACpB,oBAAC,MAAM,IAAC,KAAK,EAAE,YAAY,CAAC,GAAG,yBAAc;YAC7C,oBAAC,MAAM,IAAC,KAAK,EAAE,YAAY,CAAC,MAAM,yBAAc,CAC3C,CACZ,CAAC;QAEF,MAAM,eAAe,GAAG,CACpB,oBAAC,MAAM,IACH,YAAY,EAAE,cAAc,IAAI,IAAI,CAAC,OAAO,EAC5C,QAAQ,EAAE,CAAC,cAAmB,EAAE,EAAE,GAAG,IAAI,CAAC,QAAQ,CAAC,EAAE,cAAc,EAAE,CAAC,CAAC,CAAC,CAAC,EACzE,KAAK,EAAE,EAAE,KAAK,EAAE,EAAE,EAAE;YACpB,oBAAC,MAAM,IAAC,KAAK,EAAE,IAAI,CAAC,OAAO,QAAY;YACvC,oBAAC,MAAM,IAAC,KAAK,EAAE,IAAI,CAAC,EAAE,SAAa,CAC9B,CACZ,CAAC;QAEF,MAAM,aAAa,GAAG,CAClB,oBAAC,MAAM,IACH,YAAY,EAAE,YAAY,IAAI,IAAI,CAAC,OAAO,EAC1C,QAAQ,EAAE,CAAC,YAAiB,EAAE,EAAE,GAAG,IAAI,CAAC,QAAQ,CAAC,EAAE,YAAY,EAAE,CAAC,CAAC,CAAC,CAAC,EACrE,KAAK,EAAE,EAAE,KAAK,EAAE,EAAE,EAAE;YACpB,oBAAC,MAAM,IAAC,KAAK,EAAE,IAAI,CAAC,OAAO,QAAY;YACvC,oBAAC,MAAM,IAAC,KAAK,EAAE,IAAI,CAAC,EAAE,SAAa,CAC9B,CACZ,CAAC;QAEF,MAAM,UAAU,GAAG,CACf,oBAAC,MAAM,IACH,YAAY,EAAE,SAAS,IAAI,IAAI,CAAC,OAAO,EACvC,QAAQ,EAAE,CAAC,SAAc,EAAE,EAAE,GAAG,IAAI,CAAC,QAAQ,CAAC,EAAE,SAAS,EAAE,CAAC,CAAC,CAAC,CAAC,EAC/D,KAAK,EAAE,EAAE,KAAK,EAAE,EAAE,EAAE;YACpB,oBAAC,MAAM,IAAC,KAAK,EAAE,IAAI,CAAC,OAAO,QAAY;YACvC,oBAAC,MAAM,IAAC,KAAK,EAAE,IAAI,CAAC,EAAE,SAAa,CAC9B,CACZ,CAAC;QAGF,OAAO,CACH;YACI,2BAAG,SAAS,EAAC,SAAS,+BAAS;YAC/B,oBAAC,MAAM,IACH,YAAY,EAAE,MAAM,EACpB,KAAK,EAAE,MAAM,EACb,QAAQ,EAAE,CAAC,MAAM,EAAE,EAAE,GAAG,IAAI,CAAC,SAAS,CAAC,MAAM,CAAC,CAAA,CAAC,CAAC,GAClD;YACF,2BAAG,SAAS,EAAC,SAAS,+BAAS;YAC/B,oBAAC,OAAO,IACJ,IAAI,EAAE,CAAC,EAAE,GAAG,EAAE,MAAM,EAAE,CAAC,EACvB,QAAQ,EAAE,QAAQ,EAClB,QAAQ,EAAE,IAAI,CAAC,cAAc,GAC/B;YACF,2BAAG,SAAS,EAAC,SAAS,+BAAS;YAC/B;gBACI,oBAAC,KAAK,IACF,KAAK,EAAE,UAAU,EACjB,QAAQ,EAAE,CAAC,CAAC,EAAE,EAAE,GAAG,IAAI,CAAC,QAAQ,CAAC,EAAE,UAAU,EAAE,CAAC,CAAC,MAAM,CAAC,KAAK,EAAE,CAAC,CAAC,CAAC,CAAC,EACnE,WAAW,EAAE,gBAAgB,EAC7B,WAAW,EAAC,gCAAO,EACnB,UAAU,EAAE,eAAe,GAC7B,CACA;YACN,6BAAK,KAAK,EAAE,EAAE,SAAS,EAAE,MAAM,EAAE;gBAC7B,oBAAC,KAAK,IACF,KAAK,EAAE,QAAQ,EACf,QAAQ,EAAE,CAAC,CAAC,EAAE,EAAE,GAAG,IAAI,CAAC,QAAQ,CAAC,EAAE,QAAQ,EAAE,CAAC,CAAC,MAAM,CAAC,KAAK,EAAE,CAAC,CAAC,CAAC,CAAC,EACjE,WAAW,EAAE,cAAc,EAC3B,WAAW,EAAC,gCAAO,EACnB,UAAU,EAAE,aAAa,GAC3B,CACA;YACN,6BAAK,KAAK,EAAE,EAAE,SAAS,EAAE,MAAM,EAAE;gBAC7B,oBAAC,KAAK,IACF,KAAK,EAAE,KAAK,EACZ,QAAQ,EAAE,CAAC,CAAC,EAAE,EAAE,GAAG,IAAI,CAAC,QAAQ,CAAC,EAAE,KAAK,EAAE,CAAC,CAAC,MAAM,CAAC,KAAK,EAAE,CAAC,CAAC,CAAC,CAAC,EAC9D,WAAW,EAAC,cAAI,EAChB,WAAW,EAAC,gCAAO,EACnB,UAAU,EAAE,UAAU,GACxB,CACA,CACH,CACV,CAAC;IACN,CAAC;CACJ;AAED,eAAe,OAAO,CAAC,eAAe,EAAE,EAAE,EAAE,SAAS,EAAE,EAAE,OAAO,EAAE,IAAI,EAAE,CAAC,CAAC,WAAW,CAAC,CAAC","sourcesContent":["import * as React from 'react';\nimport { Component } from 'react';\nimport { connect } from 'react-redux';\n\nimport { IState, ImageInfo, IModuleData, IModuleConfig, HotspotInfo } from '../interface';\nimport PicLib from '../PicLib';\nimport Hotspot from '../Hotspot';\nimport { Input, Select } from 'antd';\nconst Option = Select.Option;\n\nconst mapStateToProps = (state: IState) => {\n    return {\n        moduleConfig: state.moduleConfig,\n    };\n};\n\nenum EHorizontalDir {\n    Left = \"left\",\n    Right = \"right\",\n}\n\nenum EVerticalDir {\n    Top = \"top\",\n    Bottom = \"bottom\",\n}\n\nenum Unit {\n    percent = \"%\",\n    px = \"px\",\n}\n\ninterface FixedConfigProps {\n    moduleData: IModuleData;\n    moduleConfig: IModuleConfig;\n}\n\ninterface FixedConfigState {\n    imgUrl: string;\n    hotspots: HotspotInfo[];\n    horizontal: string;\n    vertical: string;\n    width: string;\n    horizontalDir: EHorizontalDir.Left | EHorizontalDir.Right;\n    verticalDir: EVerticalDir.Top | EVerticalDir.Bottom;\n    horizontalUnit: Unit,\n    verticalUnit: Unit,\n    widthUnit: Unit,\n}\n\nclass FixedConfig extends Component<FixedConfigProps, FixedConfigState> {\n\n    constructor(props: FixedConfigProps) {\n        super(props);\n        const {\n            moduleData: {\n                data: {\n                    imgUrl,\n                    hotspots,\n                    horizontal,\n                    width,\n                    vertical,\n                    horizontalDir,\n                    verticalDir,\n                    horizontalUnit,\n                    verticalUnit,\n                    widthUnit,\n                }\n            }\n        } = props;\n        this.state = {\n            imgUrl,\n            hotspots,\n            horizontal,\n            width,\n            vertical,\n            horizontalDir,\n            verticalDir,\n            horizontalUnit,\n            verticalUnit,\n            widthUnit,\n        }\n    }\n\n\n    getConfigData = () => {\n        return this.state;\n    }\n\n    toModuleData(configData: any) {\n        const { moduleConfig } = this.props;\n        const result = Object.assign({}, moduleConfig.moduleData, {\n            data: configData,\n        });\n        return result;\n    }\n\n\n    imgChange = (imgUrl: string) => {\n        this.setState({\n            imgUrl,\n        });\n    }\n\n    hotspotsChange = (hotspots: HotspotInfo[]) => {\n        this.setState({\n            hotspots,\n        });\n    }\n\n    render() {\n        let { imgUrl,\n            hotspots,\n            horizontal,\n            vertical,\n            width,\n            horizontalDir,\n            verticalDir,\n            horizontalUnit,\n            verticalUnit,\n            widthUnit,\n        } = this.state;\n\n        const horizontalBefore = (\n            <Select\n                defaultValue={horizontalDir || EHorizontalDir.Left}\n                onChange={(horizontalDir: any) => { this.setState({ horizontalDir }); }}\n                style={{ width: 90 }}>\n                <Option value={EHorizontalDir.Left}>距左边</Option>\n                <Option value={EHorizontalDir.Right}>距右边</Option>\n            </Select>\n        );\n\n        const verticalBefore = (\n            <Select\n                defaultValue={verticalDir || EVerticalDir.Bottom}\n                onChange={(verticalDir: any) => { this.setState({ verticalDir }); }}\n                style={{ width: 90 }}>\n                <Option value={EVerticalDir.Top}>距顶部</Option>\n                <Option value={EVerticalDir.Bottom}>距底部</Option>\n            </Select>\n        );\n\n        const horizontalAfter = (\n            <Select\n                defaultValue={horizontalUnit || Unit.percent}\n                onChange={(horizontalUnit: any) => { this.setState({ horizontalUnit }); }}\n                style={{ width: 50 }}>\n                <Option value={Unit.percent}>%</Option>\n                <Option value={Unit.px}>px</Option>\n            </Select>\n        );\n\n        const verticalAfter = (\n            <Select\n                defaultValue={verticalUnit || Unit.percent}\n                onChange={(verticalUnit: any) => { this.setState({ verticalUnit }); }}\n                style={{ width: 50 }}>\n                <Option value={Unit.percent}>%</Option>\n                <Option value={Unit.px}>px</Option>\n            </Select>\n        );\n\n        const widthAfter = (\n            <Select\n                defaultValue={widthUnit || Unit.percent}\n                onChange={(widthUnit: any) => { this.setState({ widthUnit }); }}\n                style={{ width: 50 }}>\n                <Option value={Unit.percent}>%</Option>\n                <Option value={Unit.px}>px</Option>\n            </Select>\n        );\n\n\n        return (\n            <div>\n                <p className=\"d-title\">图片选择</p>\n                <PicLib\n                    defaultValue={imgUrl}\n                    value={imgUrl}\n                    onChange={(imgUrl) => { this.imgChange(imgUrl) }}\n                />\n                <p className=\"d-title\">热区配置</p>\n                <Hotspot\n                    imgs={[{ url: imgUrl }]}\n                    hotspots={hotspots}\n                    onChange={this.hotspotsChange}\n                />\n                <p className=\"d-title\">定位位置</p>\n                <div>\n                    <Input\n                        value={horizontal}\n                        onChange={(e) => { this.setState({ horizontal: e.target.value }); }}\n                        addonBefore={horizontalBefore}\n                        placeholder=\"请输入数字\"\n                        addonAfter={horizontalAfter}\n                    />\n                </div>\n                <div style={{ marginTop: '10px' }}>\n                    <Input\n                        value={vertical}\n                        onChange={(e) => { this.setState({ vertical: e.target.value }); }}\n                        addonBefore={verticalBefore}\n                        placeholder=\"请输入数字\"\n                        addonAfter={verticalAfter}\n                    />\n                </div>\n                <div style={{ marginTop: '10px' }}>\n                    <Input\n                        value={width}\n                        onChange={(e) => { this.setState({ width: e.target.value }); }}\n                        addonBefore=\"宽度\"\n                        placeholder=\"请输入数字\"\n                        addonAfter={widthAfter}\n                    />\n                </div>\n            </div >\n        );\n    }\n}\n\nexport default connect(mapStateToProps, {}, undefined, { withRef: true })(FixedConfig);\n"]}]}